{"id": 29701, "text": "Fast sell\nБыстрая продажа Freedom #779 / 43 TON (999 SUPPLY)", "date": "2025-08-13T22:06:05+00:00", "chat": "NotCoin Flags - Holders"}
{"id": 29700, "text": "📡[ **Flags**](https://cdn.stickerdom.store/6/t/1/1.png?v=0)\n📚 Notcoin\n💰 Текущий флор: **59.62 TON**\n\n[__@StickerRadarBot__](https://t.me/StickerRadarBot?start=about)", "date": "2025-08-13T22:05:16+00:00", "chat": "NotCoin Flags - Holders"}
{"id": 29699, "text": "всем здарова ,снова с вами", "date": "2025-08-13T20:47:18+00:00", "chat": "NotCoin Flags - Holders"}
{"id": 29698, "text": "🆕 Flags #317 bought on [@mrkt](https://t.me/mrkt/app?startapp=464376531)\n\n💰 54.99 TON ($193.29)\n🕐 Aug 13 23:41 (UTC +3)\n​", "date": "2025-08-13T20:43:39+00:00", "chat": "NotCoin Flags - Holders"}
{"id": 29697, "text": "🆕 Flags #601 bought on [@harbor_market_bot](https://t.me/harbor_market_bot/app?startapp=ref_464376531)\n\n💰 50.41 TON ($177.19)\n🕐 Aug 13 23:39 (UTC +3)\n​", "date": "2025-08-13T20:41:09+00:00", "chat": "NotCoin Flags - Holders"}
{"id": 29694, "text": "Продам или могу менять на флаг", "date": "2025-08-13T17:34:05+00:00", "chat": "NotCoin Flags - Holders"}
{"id": 29693, "text": "🆕 Flags #604 bought on [@palacenftbot](https://t.me/palacenftbot/app?startapp=g8SpeqxeR0)\n\n💰 50.0 TON ($171.65)\n🕐 Aug 13 18:17 (UTC +3)\n​", "date": "2025-08-13T15:19:49+00:00", "chat": "NotCoin Flags - Holders"}
{"id": 29692, "text": "бля нету там ничего сам чекни", "date": "2025-08-13T14:35:20+00:00", "chat": "NotCoin Flags - Holders"}
{"id": 29691, "text": "**1-9 Уровень рейтинга пососет что ль? ****🤔**\n\n**В коде найдена переменная, ограничивающая покупку новых подарочков ****🎁**", "date": "2025-08-13T14:30:28+00:00", "chat": "NotCoin Flags - Holders"}
{"id": 29690, "text": "Приехали", "date": "2025-08-13T14:30:28+00:00", "chat": "NotCoin Flags - Holders"}
{"id": 29689, "text": "**Not Flags**\n\n**Notcoin**\n▪️ Flags — 300 / 1099 (27.3%) [███░░░░░░░]", "date": "2025-08-13T13:23:51+00:00", "chat": "NotCoin Flags - Holders"}
{"id": 29687, "text": "Current floor prices for **Not Flags**:\n\n• **Flags** — 55.19 TON | $191.8 (on Harbor)\n\n\n#floor", "date": "2025-08-13T13:23:45+00:00", "chat": "NotCoin Flags - Holders"}
{"id": 29685, "text": "Who is selling 55 tons and why ? \nDoes he or she need money? \nOr knows anything about stickers?", "date": "2025-08-13T12:07:39+00:00", "chat": "NotCoin Flags - Holders"}
{"id": 29684, "text": "🆕 Flags #839 bought on [@palacenftbot](https://t.me/palacenftbot/app?startapp=g8SpeqxeR0)\n\n💰 55.2 TON ($194.77)\n🕐 Aug 13 14:16 (UTC +3)\n​", "date": "2025-08-13T11:19:43+00:00", "chat": "NotCoin Flags - Holders"}
{"id": 29683, "text": "Current floor prices for **Not Flags**:\n\n• **Flags** — 55.19 TON | $194.3 (on Harbor)\n\n\n#floor", "date": "2025-08-13T10:41:09+00:00", "chat": "NotCoin Flags - Holders"}
{"id": 29681, "text": "**Not Flags**\n\n**Notcoin**\n▪️ Flags — 300 / 1099 (27.3%) [███░░░░░░░]", "date": "2025-08-13T10:41:02+00:00", "chat": "NotCoin Flags - Holders"}
{"id": 29679, "text": "Понята", "date": "2025-08-13T06:25:16+00:00", "chat": "NotCoin Flags - Holders"}
{"id": 29678, "text": "3 флага еще есть", "date": "2025-08-13T06:25:15+00:00", "chat": "NotCoin Flags - Holders"}
{"id": 29677, "text": "10к звезд купил", "date": "2025-08-13T06:25:11+00:00", "chat": "NotCoin Flags - Holders"}
{"id": 29676, "text": "ради 14 авггуста", "date": "2025-08-13T06:25:08+00:00", "chat": "NotCoin Flags - Holders"}
{"id": 29675, "text": "я 1 флаг продал", "date": "2025-08-13T06:25:06+00:00", "chat": "NotCoin Flags - Holders"}
{"id": 29674, "text": "Кстати, а у тебя сколько щас флагов осталось? \nВроде как ты какую то часть тоже продал🧐", "date": "2025-08-13T06:24:59+00:00", "chat": "NotCoin Flags - Holders"}
{"id": 29673, "text": "ну бывает", "date": "2025-08-13T06:24:02+00:00", "chat": "NotCoin Flags - Holders"}
{"id": 29672, "text": "Думаю щас продать флаг свой, т.к все же настал тот день, когда деньги нужны срочно, а деньги негде взять и это хреново\nДумаю, можно будет взять другой флаг, через какое-то время\nПусть хоть и с другим номером будет у меня", "date": "2025-08-13T06:23:47+00:00", "chat": "NotCoin Flags - Holders"}
