{"id": 633, "text": "собери полное бинго из US листингов TON'а из презентации Verb\n\n\n\nкруто, что по этому направлению работа идет реально эффективно", "date": "2025-08-28T16:00:10+00:00", "chat": "/underworld"}
{"id": 632, "text": "честно, я не люблю фадить и в целом особо никогда публично не высказывался с критикой ТФ, хотя офк было за что\n\n\nно последние дни чет прям подкосили, так что возможно в ближайшее время напишу пару фад-постов про не самые очевидные проблемы если будет не лень\n\n\n\n\nа любителям fuse~~tea~~ желаю удачи и возможно вы поменяете свое мнение после того как увидите первые релизы и их токеномику :)", "date": "2025-08-28T10:25:18+00:00", "chat": "/underworld"}
