{"id": 5093, "text": "🆕 Sticker BOUGHT on [@palacenftbot](https://t.me/palacenftbot/app?startapp=g8SpeqxeR0)\n\n📝 Pengu CNY #2493 (supply 3333)\n💰 57.99 TON ($191.62)\n\n​", "date": "2025-07-21T19:25:22+00:00", "chat": "CNY PENGUINS"}
{"id": 5092, "text": "", "date": "2025-07-21T17:55:47+00:00", "chat": "CNY PENGUINS"}
{"id": 5091, "text": "", "date": "2025-07-21T17:21:24+00:00", "chat": "CNY PENGUINS"}
{"id": 5090, "text": "", "date": "2025-07-21T17:11:08+00:00", "chat": "CNY PENGUINS"}
{"id": 5089, "text": "‼️‼️ Sticker BOUGHT on [@palacenftbot](https://t.me/palacenftbot/app?startapp=g8SpeqxeR0)\n\n📝 Pengu CNY #144 (supply 3333)\n💰 75.0 TON ($247.59)\n\n​", "date": "2025-07-21T17:10:09+00:00", "chat": "CNY PENGUINS"}
{"id": 5088, "text": "🆕 Sticker BOUGHT on [@palacenftbot](https://t.me/palacenftbot/app?startapp=g8SpeqxeR0)\n\n📝 Pengu CNY #2437 (supply 3333)\n💰 57.99 TON ($190.51)\n\n​", "date": "2025-07-21T16:38:59+00:00", "chat": "CNY PENGUINS"}
{"id": 5087, "text": "Floor prices for **CNY Penguins holders**:\n\n• **Pengu CNY**: 56.10 TON\n\n#floor", "date": "2025-07-21T16:00:06+00:00", "chat": "CNY PENGUINS"}
{"id": 5086, "text": "Куплю cny pengu 49 тон", "date": "2025-07-21T14:19:40+00:00", "chat": "CNY PENGUINS"}
{"id": 5085, "text": "Куплю cny pengu 50 тон", "date": "2025-07-21T14:18:42+00:00", "chat": "CNY PENGUINS"}
{"id": 5084, "text": "", "date": "2025-07-21T12:18:12+00:00", "chat": "CNY PENGUINS"}
{"id": 5083, "text": "🆕 Sticker BOUGHT on [@palacenftbot](https://t.me/palacenftbot/app?startapp=g8SpeqxeR0)\n\n📝 Pengu CNY #1174 (supply 3333)\n💰 52.0 TON ($174.0)\n\n​", "date": "2025-07-21T08:21:51+00:00", "chat": "CNY PENGUINS"}
{"id": 5082, "text": "Floor prices for **CNY Penguins holders**:\n\n• **Pengu CNY**: 52.00 TON\n\n#floor", "date": "2025-07-21T08:00:06+00:00", "chat": "CNY PENGUINS"}
{"id": 5081, "text": "https://t.me/PudgyPenguinsRus/305", "date": "2025-07-21T07:17:49+00:00", "chat": "CNY PENGUINS"}
{"id": 5080, "text": "куплю сни пенгу - 47 ТОН", "date": "2025-07-21T06:08:52+00:00", "chat": "CNY PENGUINS"}
{"id": 5079, "text": "Floor prices for **CNY Penguins holders**:\n\n• **Pengu CNY**: 52.00 TON\n\n#floor", "date": "2025-07-21T00:00:08+00:00", "chat": "CNY PENGUINS"}
